nanokvm_mcp/__init__.py
nanokvm_mcp/auth.py
nanokvm_mcp/client.py
nanokvm_mcp/hid.py
nanokvm_mcp/server.py
iflow_mcp_scgreenhalgh_nanokvm_mcp-0.1.0.dist-info/METADATA
iflow_mcp_scgreenhalgh_nanokvm_mcp-0.1.0.dist-info/WHEEL
iflow_mcp_scgreenhalgh_nanokvm_mcp-0.1.0.dist-info/entry_points.txt
iflow_mcp_scgreenhalgh_nanokvm_mcp-0.1.0.dist-info/RECORD
