Metadata-Version: 2.4
Name: iflow-mcp-scgreenhalgh-nanokvm-mcp
Version: 0.1.0
Summary: MCP server for controlling NanoKVM devices
Requires-Python: >=3.10
Requires-Dist: httpx>=0.27.0
Requires-Dist: mcp>=1.0.0
Requires-Dist: pillow>=10.0.0
Requires-Dist: pycryptodome>=3.20.0
Requires-Dist: websockets>=12.0
Provides-Extra: dev
Requires-Dist: pytest-asyncio>=0.23.0; extra == 'dev'
Requires-Dist: pytest-cov>=4.1.0; extra == 'dev'
Requires-Dist: pytest>=8.0.0; extra == 'dev'
Provides-Extra: ocr
Requires-Dist: pytesseract>=0.3.10; extra == 'ocr'
